covalent_api/__init__.py
covalent_api/_version.py
covalent_api/class_a.py
covalent_api/class_b.py
covalent_api/pricing.py
covalent_api/session.py
covalent_api/url_utils.py
covalent_api/constants/__init__.py
covalent_api/constants/maps.py
covalent_python_api-0.0.4.dist-info/LICENSE.txt
covalent_python_api-0.0.4.dist-info/METADATA
covalent_python_api-0.0.4.dist-info/WHEEL
covalent_python_api-0.0.4.dist-info/top_level.txt
covalent_python_api-0.0.4.dist-info/RECORD
