Metadata-Version: 2.1
Name: covalent-python-api
Version: 0.0.4
Summary: Python API for Covalent.
Home-page: https://bitbucket.org/lluisBrokenC/covalent_python_api
Author: Lluis Casals Marsol
Author-email: ktmlleska@gmail.com
License: GNU General Public License v3.0 (GPLv3)
Project-URL: Documentation, https://covalent-python-api.readthedocs.io/en/latest/
Project-URL: Covalent API Documentation, https://www.covalenthq.com/docs/api/
Project-URL: Covalent Homepage, https://www.covalenthq.com/
Keywords: covalent,python,api
Platform: UNKNOWN
Classifier: License :: OSI Approved :: GNU General Public License v3 (GPLv3)
Classifier: Environment :: Console
Classifier: Intended Audience :: Developers
Classifier: Programming Language :: Python :: 3
Requires-Python: >=3.7.6, <4.0
Requires-Dist: requests (<3,>=2)
